reflex_map/__init__.py
reflex_map/map.py
reflex_map/maplibre_react.py
reflex_map/components/__init__.py
reflex_map/components/layer.py
reflex_map/components/marker.py
reflex_map/components/popup.py
reflex_map/components/source.py
reflex_map/controls/__init__.py
reflex_map/controls/fullscreen_control.py
reflex_map/controls/legend_control.py
reflex_map/controls/navigation_control.py
reflex_map/controls/search_control.py
reflex_map/controls/terrain_control.py
reflex_map-0.2.3.dist-info/METADATA
reflex_map-0.2.3.dist-info/WHEEL
reflex_map-0.2.3.dist-info/top_level.txt
reflex_map-0.2.3.dist-info/RECORD
