Metadata-Version: 2.1
Name: reflex-map
Version: 0.2.3
Summary: Reflex Map Component
Author-email: Daniel Fink & Nathan Bryant <danfink@mit.edu>, Nathan Bryant <nathan@nathanbryant.dev>
License: Apache-2.0
Project-URL: homepage, https://reflex-map.reflex.run/
Project-URL: source, https://github.com/daniel-fink/reflex-map
Keywords: reflex,reflex-custom-component,map,maplibre,mapbox,maplibre-gl,mapbox-gl
Requires-Python: >=3.10
